LICENSE
README.md
setup.cfg
setup.py
src/nautobot_plugin_builder/DrawIoNautobot.py
src/nautobot_plugin_builder/__init__.py
src/nautobot_plugin_builder/constants.py
src/nautobot_plugin_builder.egg-info/PKG-INFO
src/nautobot_plugin_builder.egg-info/SOURCES.txt
src/nautobot_plugin_builder.egg-info/dependency_links.txt
src/nautobot_plugin_builder.egg-info/requires.txt
src/nautobot_plugin_builder.egg-info/top_level.txt