Metadata-Version: 2.1
Name: nautobot-plugin-builder
Version: 1.0.0
Summary: Builds out the base of a Nautobot plugin from a draw.io database drawing
Home-page: https://github.com/GoreNetwork/draw.io-nautobot-work
Author: Daniel Himes
Author-email: dhimes@gmail.com
License: UNKNOWN
Platform: UNKNOWN
Requires-Python: >=3.7
